LICENSE.txt
README.md
setup.cfg
setup.py
headmouse/__init__.py
headmouse/headmouse.py
headmouse/headmouse_singleton.py
headmouse/headmouse_utils.py
headmouse/setup.py
headmouse.egg-info/PKG-INFO
headmouse.egg-info/SOURCES.txt
headmouse.egg-info/dependency_links.txt
headmouse.egg-info/requires.txt
headmouse.egg-info/top_level.txt
headmouse/controller/__init__.py
headmouse/controller/abstract_controller.py
headmouse/controller/keyboard_controller.py
headmouse/controller/mouse_controller.py