Metadata-Version: 2.1
Name: headmouse
Version: 1.0.6.3
Summary: An augmentative tool to use the mouse with the movement of the head.
Home-page: https://github.com/rfontalva
Download-URL: https://github.com/rfontalva/Headmouse
Author: Ramiro Fontalva
Author-email: ramirofontalva@gmail.com
License: MIT
Keywords: headmouse,HeadMouse,Headmouse,augmentative,image processing,mouse
Platform: UNKNOWN
Classifier: Development Status :: 4 - Beta
Classifier: Topic :: Scientific/Engineering :: Image Processing
Classifier: License :: OSI Approved :: MIT License
Classifier: Intended Audience :: End Users/Desktop
License-File: LICENSE.txt
